helloworld/__init__.py
helloworld/config.py
helloworld/hello.py
helloworld/images.py
helloworld/data/config/config.json
helloworld/data/images/logo.jpg
helloworld_for_pip-0.0.7.dist-info/METADATA
helloworld_for_pip-0.0.7.dist-info/WHEEL
helloworld_for_pip-0.0.7.dist-info/top_level.txt
helloworld_for_pip-0.0.7.dist-info/RECORD
